pkb/__init__.py
pkb/fast.py
pkb/routers/__init__.py
pkb/routers/browse.py
pkb/routers/misc.py
pkb/routers/search.py
pkb/templates/body
pkb/templates/error
pkb/templates/file
pkb/templates/folder
pkb/templates/header
pkb/templates/html
pkb/templates/style
pkb/utils/__init__.py
pkb/utils/app.py
pkb/utils/cache.py
pkb/utils/file_monitor.py
pkb/utils/files.py
pkb/utils/logging.py
pkb/utils/search.py
pkb-0.1.10.dist-info/METADATA
pkb-0.1.10.dist-info/WHEEL
pkb-0.1.10.dist-info/entry_points.txt
pkb-0.1.10.dist-info/RECORD
